LICENSE
MANIFEST.in
README.rst
VERSION
requirements.txt
setup.py
src/kser/__init__.py
src/kser/controller.py
src/kser/entry.py
src/kser/schemas.py
src/kser.egg-info/PKG-INFO
src/kser.egg-info/SOURCES.txt
src/kser.egg-info/dependency_links.txt
src/kser.egg-info/requires.txt
src/kser.egg-info/top_level.txt
src/kser.egg-info/zip-safe
src/kser/confluent/__init__.py
src/kser/confluent/consumer.py
src/kser/confluent/producer.py
src/kser/dummy/__init__.py
src/kser/dummy/consumer.py
src/kser/dummy/producer.py
src/kser/http/__init__.py
src/kser/http/consumer.py
src/kser/http/producer.py
src/kser/python_kafka/__init__.py
src/kser/python_kafka/consumer.py
src/kser/python_kafka/producer.py
src/kser/sequencing/__init__.py
src/kser/sequencing/operation.py
src/kser/sequencing/registry.py
src/kser/sequencing/task.py