Metadata-Version: 2.2
Name: kser
Version: 0.8.26
Summary: Kafka serialize python library
Home-page: https://github.com/cdumay/kser
Author: Cedric DUMAY
Author-email: cedric.dumay@gmail.com
License: MIT
Classifier: Programming Language :: Python
License-File: LICENSE
Requires-Dist: cdumay-error>=0.1.14
Requires-Dist: cdumay-result>=0.1.12
Provides-Extra: confluent
Requires-Dist: confluent-kafka; extra == "confluent"
Provides-Extra: http
Requires-Dist: cdumay-rest-client>=0.1; extra == "http"
Provides-Extra: pykafka
Requires-Dist: kafka-python; extra == "pykafka"
Provides-Extra: prometheus
Requires-Dist: prometheus_client; extra == "prometheus"
Provides-Extra: tests
Requires-Dist: flake8; extra == "tests"
Requires-Dist: flake8-html; extra == "tests"
Requires-Dist: pytest; extra == "tests"
Requires-Dist: pytest-cov; extra == "tests"
Requires-Dist: pytest-html; extra == "tests"
Dynamic: author
Dynamic: author-email
Dynamic: classifier
Dynamic: description
Dynamic: home-page
Dynamic: keywords
Dynamic: license
Dynamic: provides-extra
Dynamic: requires-dist
Dynamic: summary
